pyshine/__init__.py
pyshine/convenience.py
pyshine-0.0.9.dist-info/LICENSE
pyshine-0.0.9.dist-info/METADATA
pyshine-0.0.9.dist-info/WHEEL
pyshine-0.0.9.dist-info/entry_points.txt
pyshine-0.0.9.dist-info/top_level.txt
pyshine-0.0.9.dist-info/RECORD
