Metadata-Version: 2.1
Name: pyshine
Version: 0.0.9
Summary: This library contains various Audio and Video Signal Processing utilities
Home-page: https://github.com/py2ai/pyshine_streamer.git
Author: PyShine
Author-email: python2ai@gmail.com
License: MIT
Platform: UNKNOWN
Classifier: License :: OSI Approved :: MIT License
Classifier: Programming Language :: Python :: 3.6
Classifier: Programming Language :: Python :: 3.7
Classifier: Programming Language :: Python :: 3.8
